Hunabku-0.0.16.data/scripts/hunabku_server
hunabku/Config.py
hunabku/Hunabku.py
hunabku/HunabkuBase.py
hunabku/PluginGenerator.py
hunabku/__init__.py
hunabku/_version.py
hunabku/config/apidoc-header.md
hunabku/config/apidoc.json
hunabku/config/errors.json
hunabku/templates/__init__.py
hunabku/templates/apidoc.html
hunabku/templates/plugin/HunabKu_template/MANIFEST.in
hunabku/templates/plugin/HunabKu_template/README.md
hunabku/templates/plugin/HunabKu_template/setup.py
hunabku/templates/plugin/HunabKu_template/hunabku_template/__init__.py
hunabku/templates/plugin/HunabKu_template/hunabku_template/_version.py
hunabku/templates/plugin/HunabKu_template/hunabku_template/endpoints/Hello.py
Hunabku-0.0.16.dist-info/LICENSE
Hunabku-0.0.16.dist-info/METADATA
Hunabku-0.0.16.dist-info/WHEEL
Hunabku-0.0.16.dist-info/top_level.txt
Hunabku-0.0.16.dist-info/RECORD
