Metadata-Version: 2.1
Name: Hunabku
Version: 0.0.16
Summary: Modular APIs creation using plugins system
Home-page: https://github.com/colav/Hunabku
Author: Colav
Author-email: colav@udea.edu.co
License: BSD
Requires-Python: >3.8
License-File: LICENSE
Requires-Dist: flask >=1.1.2
Requires-Dist: requests >=2.22.0
Provides-Extra: scienti
Requires-Dist: hunabku-scienti ; extra == 'scienti'
